boilerpipy/compat.py
boilerpipy/error.py
boilerpipy/__init__.py
boilerpipy/common.py
boilerpipy/expressions.py
boilerpipy-0.2.5.data/scripts/readability
boilerpipy-0.2.5.data/scripts/query
boilerpipy-0.2.5.dist-info/metadata.json
boilerpipy-0.2.5.dist-info/METADATA
boilerpipy-0.2.5.dist-info/RECORD
boilerpipy-0.2.5.dist-info/WHEEL
boilerpipy-0.2.5.dist-info/top_level.txt
boilerpipy-0.2.5.dist-info/DESCRIPTION.rst
