Metadata-Version: 2.0
Name: boilerpipy
Version: 0.2.5
Summary: Readability/Boilerpipe extractor in Python
Home-page: https://github.com/harshavardhana/boilerpipy.git
Author: Harshavardhana
Author-email: harsha@harshavardhana.net
License: Apache
Platform: any
Classifier: Development Status :: 5 - Production/Stable
Classifier: Intended Audience :: Developers
Classifier: License :: OSI Approved :: Apache Software License
Classifier: Programming Language :: Python
Classifier: Topic :: Software Development :: Libraries :: Python Modules
Requires-Dist: lxml
Requires-Dist: beautifulsoup4
Requires-Dist: urlparse2
